[
	{
		"title": "MTB Sunshine R29 Negro/Naranja/Celeste Talle S",
		"description": "MTB Sunshine R29 Negro/Naranja/Celeste Talle S",
		"code": 1,
		"thumbnail": "https://www.topmega.com.ar/media/catalog/product/2/_/2_18_1_1.jpg?optimize=high&bg-color=255,255,255&fit=bounds&height=&width=&canvas=:",
		"price": 116999,
		"stock": 10,
		"id": 1
	},
	{
		"title": "MTB Sunshine R29 Negro/Naranja/Celeste Talle S",
		"description": "MTB Sunshine R29 Negro/Naranja/Celeste Talle S",
		"code": 1,
		"thumbnail": "https://www.topmega.com.ar/media/catalog/product/2/_/2_18_1_1.jpg?optimize=high&bg-color=255,255,255&fit=bounds&height=&width=&canvas=:",
		"price": 116999,
		"stock": 10,
		"id": 2
	},
	{
		"title": "MTB Sunshine R29 Negro/Naranja/Celeste Talle S",
		"description": "MTB Sunshine R29 Negro/Naranja/Celeste Talle S",
		"code": 1,
		"thumbnail": "https://www.topmega.com.ar/media/catalog/product/2/_/2_18_1_1.jpg?optimize=high&bg-color=255,255,255&fit=bounds&height=&width=&canvas=:",
		"price": 116999,
		"stock": 10,
		"id": 3
	}
]